log.py
machine.py
music.py
neopixel.py
os.py
power.py
radio.py
speech.py
utime.py
archive/random.py
microbit/SoundEvent.py
microbit/__init__.py
microbit/accelerometer.py
microbit/audio.py
microbit/compass.py
microbit/display.py
microbit/i2c.py
microbit/microphone.py
microbit/speaker.py
microbit/spi.py
microbit/uart.py
tests/imports.py
venv/bin/activate_this.py
pseudo_microbit-1.12.dist-info/LICENSE
pseudo_microbit-1.12.dist-info/METADATA
pseudo_microbit-1.12.dist-info/WHEEL
pseudo_microbit-1.12.dist-info/top_level.txt
pseudo_microbit-1.12.dist-info/RECORD
