Metadata-Version: 2.1
Name: pseudo-microbit
Version: 1.12
Summary: A pseudo implementation of the micro:bit micropython API.
Author-email: Alan Yorinks <MisterYsLab@gmail.com>
License: AGPL-3.0-or-later
Keywords: micro:bit,micropython
Classifier: Development Status :: 5 - Production/Stable
Classifier: Environment :: Other Environment
Classifier: Intended Audience :: Developers
Classifier: Intended Audience :: Education
Classifier: Operating System :: OS Independent
Classifier: Topic :: Software Development :: Libraries :: Python Modules
Requires-Python: >=3.8
License-File: LICENSE
Requires-Dist: microfs
Requires-Dist: uflash
Requires-Dist: python-minimizer
